zephyr/__init__.py
zephyr/_types.py
zephyr/exceptions.py
zephyr/app/__init__.py
zephyr/app/_callables.py
zephyr/app/_compat.py
zephyr/app/_exception_handler.py
zephyr/app/_utils.py
zephyr/app/application.py
zephyr/app/background.py
zephyr/app/concurrency.py
zephyr/app/convertors.py
zephyr/app/datastructures.py
zephyr/app/encoders.py
zephyr/app/exceptions.py
zephyr/app/formparsers.py
zephyr/app/requests.py
zephyr/app/responses.py
zephyr/app/routing.py
zephyr/app/websockets.py
zephyr/app/dependencies/__init__.py
zephyr/app/dependencies/models.py
zephyr/app/dependencies/utils.py
zephyr/app/middleware/__init__.py
zephyr/app/middleware/base.py
zephyr/app/middleware/cache.py
zephyr/app/middleware/compression.py
zephyr/app/middleware/cors.py
zephyr/app/middleware/metrics.py
zephyr/app/middleware/rate_limit.py
zephyr/app/middleware/request_id.py
zephyr/app/middleware/tracing.py
zephyr/app/middleware/websocket.py
zephyr/app/params/__init__.py
zephyr/app/params/body.py
zephyr/app/params/param.py
zephyr/app/security/__init__.py
zephyr/app/security/api_key.py
zephyr/app/security/base.py
zephyr/app/security/http.py
zephyr/app/security/oauth2.py
zephyr/app/security/open_id_connect_url.py
zephyr/app/security/utils.py
zephyr/conf/__init__.py
zephyr/conf/base.py
zephyr/conf/manager.py
zephyr/core/__init__.py
zephyr/core/loops.py
zephyr/core/logging/__init__.py
zephyr/core/logging/constants.py
zephyr/core/logging/formatter.py
zephyr/core/logging/logger.py
zephyr/core/reloader/__init__.py
zephyr/core/zserver/__init__.py
zephyr/core/zserver/config.py
zephyr/core/zserver/lifespan.py
zephyr/core/zserver/server.py
zephyr/core/zserver/state.py
zephyr/core/zserver/net/__init__.py
zephyr/core/zserver/net/buffer.py
zephyr/core/zserver/net/connection.py
zephyr/core/zserver/net/constants.py
zephyr/core/zserver/net/exceptions.py
zephyr/core/zserver/net/flow_control.py
zephyr/core/zserver/net/unreader.py
zephyr/core/zserver/protocol/__init__.py
zephyr/core/zserver/protocol/http/__init__.py
zephyr_py-0.1.0.dev2.dist-info/METADATA
zephyr_py-0.1.0.dev2.dist-info/WHEEL
zephyr_py-0.1.0.dev2.dist-info/entry_points.txt
zephyr_py-0.1.0.dev2.dist-info/licenses/LICENSE
zephyr_py-0.1.0.dev2.dist-info/RECORD
