Metadata-Version: 2.4
Name: zephyr-py
Version: 0.1.0.dev2
Summary: A modern, high-performance Python web framework with advanced developer tools and enterprise-grade capabilities
Author-email: A M <am@gmail.com>
License: Business Source License 1.1
License-File: LICENSE
Keywords: async,enterprise,framework,ldap,web
Classifier: Development Status :: 3 - Alpha
Classifier: Intended Audience :: Developers
Classifier: License :: Other/Proprietary License
Classifier: Programming Language :: Python :: 3
Classifier: Programming Language :: Python :: 3.11
Classifier: Programming Language :: Python :: 3.12
Classifier: Topic :: Internet :: WWW/HTTP :: HTTP Servers
Classifier: Topic :: Software Development :: Libraries :: Application Frameworks
Requires-Python: <4.0,>=3.11
Requires-Dist: aiosmtplib>=2.0.0
Requires-Dist: anyio>=4.9.0
Requires-Dist: click>=8.0.0
Requires-Dist: cryptography>=41.0.0
Requires-Dist: ldap3>=2.9.1
Requires-Dist: passlib[bcrypt]>=1.7.4
Requires-Dist: pydantic-settings>=2.0.0
Requires-Dist: pydantic>=2.11.2
Requires-Dist: pyotp>=2.9.0
Requires-Dist: pytest-asyncio>=0.18.0
Requires-Dist: pytest>=7.0.0
Requires-Dist: python-jose[cryptography]>=3.3.0
Requires-Dist: python-keycloak>=3.0.0
Requires-Dist: python-multipart>=0.0.20
Requires-Dist: qrcode>=7.4.2
Requires-Dist: sqlalchemy>=2.0.0
Requires-Dist: twine>=6.2.0
Requires-Dist: typing-extensions>=4.0.0
Requires-Dist: webauthn>=1.11.0
Requires-Dist: websockets>=13.0
Provides-Extra: dev
Requires-Dist: black>=25.1.0; extra == 'dev'
Requires-Dist: isort>=5.10.0; extra == 'dev'
Requires-Dist: mypy>=1.0.0; extra == 'dev'
Requires-Dist: pytest-asyncio>=0.18.0; extra == 'dev'
Requires-Dist: pytest-cov>=4.0.0; extra == 'dev'
Requires-Dist: pytest-mock>=3.10.0; extra == 'dev'
Requires-Dist: pytest-xdist>=3.0.0; extra == 'dev'
Requires-Dist: pytest>=7.0.0; extra == 'dev'
Requires-Dist: ruff>=0.13.3; extra == 'dev'
Provides-Extra: performance
Requires-Dist: uvloop>=0.21.0; (sys_platform != 'win32') and extra == 'performance'
Provides-Extra: stubs
Requires-Dist: mypy>=1.0.0; extra == 'stubs'
Requires-Dist: types-cryptography>=3.0.0; extra == 'stubs'
Requires-Dist: types-passlib>=1.7.0; extra == 'stubs'
Requires-Dist: types-python-jose>=3.3.0; extra == 'stubs'
Requires-Dist: types-requests>=2.31.0; extra == 'stubs'
